lmrt4u/__init__.py
lmrt4u/__main__.py
lmrt4u/controller.py
lmrt4u/entry.py
lmrt4u/helpers.py
lmrt4u/initializer.py
lmrt4u/interface.py
lmrt4u/loader.py
lmrt4u/parser.py
lmrt4u/renderer.py
lmrt4u/tuples.py
lmrt4u/validator.py
lmrt4u_dbneal-0.0.3.dist-info/LICENSE
lmrt4u_dbneal-0.0.3.dist-info/METADATA
lmrt4u_dbneal-0.0.3.dist-info/WHEEL
lmrt4u_dbneal-0.0.3.dist-info/top_level.txt
lmrt4u_dbneal-0.0.3.dist-info/RECORD
