Metadata-Version: 2.1
Name: lmrt4u-dbneal
Version: 0.0.3
Summary: Agile project artefact generator.
Home-page: https://github.com/dbneal/lmrt4u
Author: Dillon ONeal
Author-email: doneal@csu.fullerton.edu
License: UNKNOWN
Platform: UNKNOWN
Classifier: Programming Language :: Python :: 3
Classifier: License :: OSI Approved :: MIT License
Classifier: Operating System :: OS Independent
Requires-Dist: pyfiglet
Requires-Dist: clint
Requires-Dist: six
Requires-Dist: matplotlib
Requires-Dist: asciiplotlib
Requires-Dist: cerberus
Requires-Dist: colorama
Requires-Dist: termcolor
Requires-Dist: numpy
Requires-Dist: pyinquirer
